README.md
setup.py
hpolib/__init__.py
hpolib/__version__.py
hpolib/abstract_benchmark.py
hpolib/abstract_multitask_benchmark.py
hpolib/config.py
hpolib/benchmarks/__init__.py
hpolib/benchmarks/ml/__init__.py
hpolib/benchmarks/ml/autosklearn_benchmark.py
hpolib/benchmarks/ml/bnn_benchmark.py
hpolib/benchmarks/ml/conv_net.py
hpolib/benchmarks/ml/fully_connected_network.py
hpolib/benchmarks/ml/logistic_regression.py
hpolib/benchmarks/ml/residual_networks.py
hpolib/benchmarks/ml/sklearn_mlp_benchmark.py
hpolib/benchmarks/ml/svm_benchmark.py
hpolib/benchmarks/rl/__init__.py
hpolib/benchmarks/rl/cartpole.py
hpolib/benchmarks/surrogates/__init__.py
hpolib/benchmarks/surrogates/cnn.py
hpolib/benchmarks/surrogates/paramnet.py
hpolib/benchmarks/surrogates/surrogate_benchmark.py
hpolib/benchmarks/surrogates/svm.py
hpolib/benchmarks/surrogates/wide_resnet_2d.py
hpolib/benchmarks/synthetic_functions/__init__.py
hpolib/benchmarks/synthetic_functions/bohachevsky.py
hpolib/benchmarks/synthetic_functions/branin.py
hpolib/benchmarks/synthetic_functions/camelback.py
hpolib/benchmarks/synthetic_functions/counting_ones.py
hpolib/benchmarks/synthetic_functions/forrester.py
hpolib/benchmarks/synthetic_functions/goldstein_price.py
hpolib/benchmarks/synthetic_functions/hartmann3.py
hpolib/benchmarks/synthetic_functions/hartmann6.py
hpolib/benchmarks/synthetic_functions/levy.py
hpolib/benchmarks/synthetic_functions/rosenbrock.py
hpolib/benchmarks/synthetic_functions/sin_one.py
hpolib/benchmarks/synthetic_functions/sin_two.py
hpolib/benchmarks/synthetic_functions/wrapper/__init__.py
hpolib/benchmarks/synthetic_functions/wrapper/synthetic_noise_and_cost.py
hpolib/util/__init__.py
hpolib/util/data_manager.py
hpolib/util/dependencies.py
hpolib/util/openml_data_manager.py
hpolib/util/rng_helper.py
hpolib2.egg-info/PKG-INFO
hpolib2.egg-info/SOURCES.txt
hpolib2.egg-info/dependency_links.txt
hpolib2.egg-info/requires.txt
hpolib2.egg-info/top_level.txt
tests/__init__.py
tests/test_abstract_benchmark.py
tests/test_config.py
tests/test_data_manager.py
tests/test_openml_data_manager.py
tests/test_synthetic_functions.py
tests/test_ml/__init__.py
